libsstv/__init__.py
libsstv/sstv_decoder.py
libsstv/sstv_modes.py
libsstv-1.0.0.dist-info/licenses/LICENSE
libsstv-1.0.0.dist-info/METADATA
libsstv-1.0.0.dist-info/WHEEL
libsstv-1.0.0.dist-info/top_level.txt
libsstv-1.0.0.dist-info/RECORD
